mpycntrl/__init__.py
mpycntrl/__main__.py
mpycntrl/mpycntrl.py
mpycntrl/sample_pttyws.py
mpycntrl/sync.py
mpycntrl/util.py
mpycntrl-0.0.10.dist-info/LICENSE.md
mpycntrl-0.0.10.dist-info/METADATA
mpycntrl-0.0.10.dist-info/WHEEL
mpycntrl-0.0.10.dist-info/entry_points.txt
mpycntrl-0.0.10.dist-info/top_level.txt
mpycntrl-0.0.10.dist-info/RECORD
