Metadata-Version: 2.1
Name: mpycntrl
Version: 0.0.10
Summary: Control MicroPython with your own code
Home-page: https://github.com/kr-g/mpycntrl
Author: k. goger
Author-email: k.r.goger+mpycntrl@gmail.com
License: MIT
Keywords: micropython utility shell
Classifier: Development Status :: 3 - Alpha
Classifier: Operating System :: POSIX :: Linux
Classifier: Environment :: Console
Classifier: Intended Audience :: Developers
Classifier: Topic :: Software Development :: Embedded Systems
Classifier: Topic :: Terminals :: Serial
Classifier: Topic :: Utilities
Classifier: Programming Language :: Python :: 3
Classifier: License :: OSI Approved :: MIT License
Requires-Python: >=3.8
License-File: LICENSE.md
Requires-Dist: pyserial
Requires-Dist: pttydev
